# 4. 线程的同步与死锁

## 1. 同步问题的引出

需求：多个线程同时卖票



```
/**
 * 多个线程同时卖票
 */
public class Demo01 {
    public static void main(String[] args) {
        MyThread mt = new MyThread();
        new Thread(mt,"黄牛1").start();
        new Thread(mt,"黄牛2").start();
        new Thread(mt,"黄牛3").start();

    }
}

class MyThread implements Runnable {
    private int ticket = 10; //一共10张票

    @Override
    public void run() {
        while (this.ticket > 0) { //还有票
            try {
                Thread.sleep(200);
            } catch (InterruptedException e) {
                e.printStackTrace();
            } //模拟网络延迟
            System.out.println(Thread.currentThread().getName()+",还有" + this.ticket-- + "张票");

        }
    }
}
```



这个时候我们发现，票数竟然出现负数，这种问题我们称之为**不同步**操作。
**不同步的唯一好处是处理速度快（多个线程并发执行）**





## 2. 同步处理

所谓的同步指的是所有的线程不是一起进入到方法中执行，而是按照顺序一个一个进来。

### 2.1 synchronized 处理同步问题

如果要想实现这把"锁"的功能，可以采用关键字synchronized来处理。
使用synchronized关键字处理有两种模式：同步代码块、同步方法



范例：使用同步代码块 : 如果要使用同步代码块必须设置一个要锁定的对象，所以一般可以锁定当前对象:this



```
package com.xuwei.threadSynchronous;

/**
 * 多个线程同时卖票
 */
public class Demo02 {
    public static void main(String[] args) {
        MyThread2 mt = new MyThread2();
        Thread t1 = new Thread(mt, "黄牛A");
        Thread t2 = new Thread(mt, "黄牛B");
        Thread t3 = new Thread(mt, "黄牛C");
        t1.setPriority(Thread.MIN_PRIORITY);
        t2.setPriority(Thread.MAX_PRIORITY);
        t3.setPriority(Thread.MAX_PRIORITY);

        t1.start();
        t2.start();
        t3.start();

    }
}

class MyThread2 implements Runnable {
    private int ticket = 100; //一共100张票

    @Override
    public void run() {
        for (int i = 0; i < 100; i++) {
            //在同一时刻，只允许一个线程进入代码块处理
            synchronized (this) { //表示为程序逻辑上锁
                if (this.ticket > 0) {
                    try {
                        Thread.sleep(20);
                    } catch (InterruptedException e) {
                        e.printStackTrace();
                    } //模拟网络延迟
                    System.out.println(Thread.currentThread().getName()+",还有"+this.ticket -- +" 张票");
                }
            }
        }
    }
}
```



第一种方式是在方法里拦截的，也就是说进入到方法中的线程依然可能会有多个



范例：使用同步方法



```
package com.xuwei.threadSynchronous;

/**
 * 多个线程同时卖票
 */
public class Demo03 {
    public static void main(String[] args) {
        MyThread3 mt = new MyThread3();
        Thread t1 = new Thread(mt, "黄牛A");
        Thread t2 = new Thread(mt, "黄牛B");
        Thread t3 = new Thread(mt, "黄牛C");
        t1.setPriority(Thread.MIN_PRIORITY);
        t2.setPriority(Thread.MAX_PRIORITY);
        t3.setPriority(Thread.MAX_PRIORITY);

        t1.start();
        t2.start();
        t3.start();

    }
}

class MyThread3 implements Runnable {
    private int ticket = 100; //一共100张票

    @Override
    public void run() {
        for (int i = 0; i < 100; i++) {
            this.sale();
        }
    }

    private synchronized void sale() {
        if (this.ticket > 0) { // 还有票
            try {
                Thread.sleep(20);
            } catch (InterruptedException e) {
// TODO Auto-generated catch block
                e.printStackTrace();
            } // 模拟网络延迟
            System.out.println(Thread.currentThread().getName() + ",还有" + this.ticket-- + " 张票");
        }
    }
}
```



**同步虽然可以保证数据的完整性（线程安全操作），但是其执行的速度会很慢。**

**
**

练习：启动多个线程打印如下序列：*@#Thread名*@#Thread名..........



```
package com.xuwei.threadSynchronous;

public class Demo04 {
    public static void main(String[] args) {
        MyThread4 mt = new MyThread4();
        Thread t1 = new Thread(mt, "线程1");
        Thread t2 = new Thread(mt, "线程2");
        Thread t3 = new Thread(mt, "线程3");

        t1.start();
        t2.start();
        t3.start();

    }
}

class MyThread4 implements Runnable {
    @Override
    public void run() {
        for (int i = 0; i < 5; i++) {
            this.printName();
        }
    }

    public synchronized void printName() {
        System.out.println("*@#" + Thread.currentThread().getName());
    }
}
```





### 2.2 关于 synchronized 的额外说明

范例：观察 synchronized 锁多对象



```
package com.xuwei.threadSynchronous;

public class Demo05 {
    public static void main(String[] args) {
        for (int i = 0; i < 3; i++) {
            MyThread5 mt = new MyThread5();
            mt.start();
        }
    }
}

class Sync {
    public synchronized void test() {
        System.out.println("test方法开始，当前线程为 "+Thread.currentThread().getName());
        try {
            Thread.sleep(1000);
        } catch (InterruptedException e) {
            e.printStackTrace();
        }
        System.out.println("test方法结束，当前线程为 "+Thread.currentThread().getName());
    }
}

class MyThread5 extends Thread {
    @Override
    public void run() {
        Sync sync = new Sync();
        sync.test();
    }
}
```



通过上述代码以及运行结果我们可以发现，没有看到synchronized起到作用，三个线程同时运行test()方法。

**实际上，****synchronized(this)****以及非****static****的****synchronized****方法，只能防止多个线程同时执行同一个对象的同步
代码段。即****synchronized****锁住的是括号里的对象，而不是代码。对于非****static****的****synchronized****方法，锁的就是对
象本身也就是****this****。**

当synchronized锁住一个对象后，别的线程如果也想拿到这个对象的锁，就必须等待这个线程执行完成释放锁，才
能再次给对象加锁，这样才达到线程同步的目的。即使两个不同的代码段，都要锁同一个对象，那么这两个代码段
也不能在多线程环境下同时运行。



那么，如果真要锁住这段代码，要怎么做?

1. 锁住同一个对象
2. 让 synchronized 锁这个类对应的 Class 对象。



范例：锁同一个对象



```
package com.xuwei.threadLock;

public class Demo01 {
    public static void main(String[] args) {
        Sync sync = new Sync();
        for (int i = 0; i < 3; i++) {
            MyThread mt = new MyThread(sync);
            mt.start();
        }
    }
}

class Sync {
    public void test() {
        synchronized (this) {
            System.out.println("test方法开始，当前线程为 "+Thread.currentThread().getName());
            try {
                Thread.sleep(1000);
            } catch (InterruptedException e) {
                e.printStackTrace();
            }
            System.out.println("test方法结束，当前线程为 "+Thread.currentThread().getName());
        }
    }
}

class MyThread extends Thread {
    private Sync sync;
    public MyThread(Sync sync) {
        this.sync = sync;
    }
    @Override
    public void run() {
        this.sync.test();
    }
}
```



范例：全局锁



```
package com.xuwei.threadLock;

public class Demo02 {
    public static void main(String[] args) {
        for (int i = 0; i < 3; i++) {
            MyThread2 mt = new MyThread2();
            mt.start();
        }
    }
}

class Sync2 {
    public void test() {
        synchronized (Sync2.class) {
            System.out.println("test方法开始，当前线程为 " +
                    Thread.currentThread().getName());
            try {
                Thread.sleep(1000);
            } catch (InterruptedException e) {
                e.printStackTrace();
            }
            System.out.println("test方法结束，当前线程为 " + Thread.currentThread().getName());
        }
    }
}

class MyThread2 extends Thread {
    @Override
    public void run() {
        Sync2 sync = new Sync2();
        sync.test();
    }
}
```



上面代码用synchronized(Sync.class)实现了全局锁的效果。因此，**如果要想锁的是代码段，锁住多个对象的同一**

**方法，使用这种全局锁，锁的是类而不是this。**

static synchronized方法，static方法可以直接类名加方法名调用，方法中无法使用this，所以它锁的不是this，而是

类的Class对象，所以，**static synchronized方法也相当于全局锁，相当于锁住了代码段。**

**
**

**
**

### 2.3 synchronized 实现原理

先来看一段简单的代码：



```
public class Test{
    private static Object object = new Object();
    public static void main(String[] args) {
        synchronized (object) {
            System.out.println("hello world");
        }
    }
}
```



下面我们使用javap反编译后看看生成的部分字节码



```
public static void main(java.lang.String[]);
    descriptor: ([Ljava/lang/String;)V
    flags: ACC_PUBLIC, ACC_STATIC
    Code:
      stack=2, locals=3, args_size=1
        0: getstatic #2 // Field object:Ljava/lang/Object;
        3: dup
        4: astore_1
        5: monitorenter // 瞪大眼睛看这里！！！
        6: getstatic #3 // Field
java/lang/System.out:Ljava/io/PrintStream;
        9: ldc #4 // String hello world
        11: invokevirtual #5 // Method java/io/PrintStream.println:
(Ljava/lang/String;)V
        14: aload_1
        15: monitorexit // 瞪大眼睛看这里！！！
        16: goto 24
        19: astore_2
        20: aload_1
        21: monitorexit // 瞪大眼睛看这里！！！
        22: aload_2
        23: athrow
        24: return
      Exception table:
        from to target type
            6 16 19 any
            19 22 19 any
```



执行同步代码块后首先要先执行monitorenter指令，退出的时候monitorexit指令。通过分析之后可以看出，使用

Synchronized进行同步，**其关键就是必须要对对象的监视器monitor进行获取，当线程获取monitor后才能继续往**

**下执行，否则就只能等待。而这个获取的过程是互斥的，即同一时刻只有一个线程能够获取到monitor。**

**
**

**
**不知道大家是否注意到上述字节码中包含一个monitorenter指令以及多个monitorexit指令。这是因为Java虚拟机

需要确保所获得的锁在正常执行路径，以及异常执行路径上都能够被解锁。



下面在看看Synchronized修饰的同步方法又会进行怎样的操作？



```
public synchronized void foo() {
    System.out.println("hello world");
}

public synchronized void foo();
    descriptor: ()V
    flags: ACC_PUBLIC, ACC_SYNCHRONIZED // look!!!!!
    Code:
        stack=2, locals=1, args_size=1
            0: getstatic #5 // Field
java/lang/System.out:Ljava/io/PrintStream;
            3: ldc #6 // String hello world
            5: invokevirtual #7 // Method java/io/PrintStream.println:
(Ljava/lang/String;)V
            8: return
        LineNumberTable:
            line 9: 0
            line 10: 8
}
```



当用 synchronized 标记方法时，你会看到字节码中方法的访问标记包括 ACC_SYNCHRONIZED。该标记表示在进

入该方法时，Java 虚拟机需要进行 monitorenter 操作。而在退出该方法时，不管是正常返回，还是向调用者抛异

常，Java 虚拟机均需要进行 monitorexit 操作。



这里 monitorenter 和 monitorexit 操作所对应的锁对象是隐式的。对于实例方法来说，这两个操作对应的锁对象

是 this；对于静态方法来说，这两个操作对应的锁对象则是所在类的 Class 实例。



关于 monitorenter 和 monitorexit 的作用，我们可以抽象地理解为每个锁对象拥有一个锁计数器和一个指向持有

该锁的线程的指针。



当执行 monitorenter 时，如果目标锁对象的计数器为 0，那么说明它没有被其他线程所持有。在这个情况下，

Java 虚拟机会将该锁对象的持有线程设置为当前线程，并且将其计数器加 1。

在目标锁对象的计数器不为 0 的情况下，如果锁对象的持有线程是当前线程，那么 Java 虚拟机可以将其计数器加

1，否则需要等待，直至持有线程释放该锁。



当执行 monitorexit 时，Java 虚拟机则需将锁对象的计数器减 1。当计数器减为 0 时，那便代表该锁已经被释放掉

了。



之所以采用这种计数器的方式，是为了允许同一个线程重复获取同一把锁。举个例子，如果一个 Java 类中拥有多

个 synchronized 方法，那么这些方法之间的相互调用，不管是直接的还是间接的，都会涉及对同一把锁的重复加

锁操作。因此，我们需要设计这么一个可重入的特性，来避免编程里的隐式约束。





### 2.3 JDK1.5 提供的Lock锁

范例：使用ReentrantLock进行同步处理



```
package com.xuwei.threadLock;

import java.util.concurrent.locks.Lock;
import java.util.concurrent.locks.ReentrantLock;

public class Demo03 {
    public static void main(String[] args) {
        MyThread3 mt = new MyThread3();
        Thread t1 = new Thread(mt, "黄牛A");
        Thread t2 = new Thread(mt, "黄牛B");
        Thread t3 = new Thread(mt, "黄牛C");
        t1.setPriority(Thread.MIN_PRIORITY);
        t2.setPriority(Thread.MAX_PRIORITY);
        t3.setPriority(Thread.MAX_PRIORITY);
        t1.start();
        t2.start();
        t3.start();
    }
}

class MyThread3 implements Runnable {
    private int ticket = 100;
    private Lock ticketLock = new ReentrantLock();

    @Override
    public void run() {
        for (int i = 0; i < 500; i++) {
            ticketLock.lock();
            try {
                if (this.ticket > 0) { //还有票
                    try {
                        Thread.sleep(20);
                    } catch (InterruptedException e) {
                        e.printStackTrace();
                    }
                    System.out.println(Thread.currentThread().getName() + ",还有" +
                            this.ticket-- + " 张票");
                }
            } finally {
                ticketLock.unlock();
            }
        }
    }
}
```



使用 Java 提供的 Lock 对象，相比 synchronized 来说性能更高。





### 2.4 synchronized 优化

现在我们对Synchronized应该有所印象了，它最大的特征就是在同一时刻只有一个线程能够获得对象的监视器（monitor），从而进入到同步代码块或者同步方法之中，即表现为互斥性（排它性）。这种方式肯定效率低下，每次只能通过一个线程，既然每次只能通过一个，这种形式不能改变的话，那么我们能不能让每次通过的速度变快一点呢



打个比方，去收银台付款，之前的方式是，大家都去排队，然后取纸币付款收银员找零，有的时候付款的时候在包里拿出钱包再去拿出钱，这个过程是比较耗时的，然后，支付宝解放了大家去钱包找钱的过程，现在只需要扫描下就可以完成付款了，也省去了收银员跟你找零的时间的了。同样是需要排队，但整个付款的时间大大缩短，是不是整体的效率变高速率变快了？这种优化方式同样可以引申到锁优化上，缩短获取锁的时间。



在聊到锁的优化也就是锁的几种状态前，有两个知识点需要先关注：

（1）CAS操作

（2）Java对象头，这是理解下面知识的前提条件。

#### 2.4.1 CAS 操作

**什么是CAS？** 

使用锁时，线程获取锁是一种悲观锁策略，即假设每一次执行临界区代码都会产生冲突，所以当前线程获取到锁的

时候同时也会阻塞其他线程获取该锁。而CAS操作（又称为无锁操作）是一种乐观锁策略，它假设所有线程访问共

享资源的时候不会出现冲突，既然不会出现冲突自然而然就不会阻塞其他线程的操作。因此，线程就不会出现阻塞

停顿的状态。那么，如果出现冲突了怎么办？无锁操作是使用CAS(compare and swap)又叫做比较交换来鉴别线

程是否出现冲突，出现冲突就重试当前操作直到没有冲突为止。



**CAS的操作过程** 

CAS比较交换的过程可以通俗的理解为CAS(V,O,N)，包含三个值分别为：V 内存地址存放的实际值；O 预期的值

（旧值）；N 更新的新值。当V和O相同时，也就是说旧值和内存中实际的值相同表明该值没有被其他线程更改

过，即该旧值O就是目前来说最新的值了，自然而然可以将新值N赋值给V。反之，V和O不相同，表明该值已经被

其他线程改过了则该旧值O不是最新版本的值了，所以不能将新值N赋给V，返回V即可。当多个线程使用CAS操作

一个变量是，只有一个线程会成功，并成功更新，其余会失败。失败的线程会重新尝试，当然也可以选择挂起线

程。



CAS的实现需要硬件指令集的支撑，在JDK1.5后虚拟机才可以使用处理器提供的CMPXCHG指令实现。



元老级的Synchronized(未优化前)最主要的问题是：在存在线程竞争的情况下会出现线程阻塞和唤醒锁带来的性能

问题，因为这是一种互斥同步（阻塞同步）。而CAS并不是武断的将线程挂起，当CAS操作失败后会进行一定的尝

试，而非进行耗时的挂起唤醒的操作，因此也叫做非阻塞同步。这是两者主要的区别



**CAS的问题** 

1. ABA问题 因为CAS会检查旧值有没有变化，这里存在这样一个有意思的问题。比如一个旧值A变为了成B，然后再变成A，刚好在做CAS时检查发现旧值并没有变化依然为A，但是实际上的确发生了变化。解决方案可以沿袭数据库中常用的乐观锁方式，添加一个版本号可以解决。在JDK1.5后的atomic包中提供了AtomicStampedReference来解决ABA问题，解决思路就是这样的。
2. 自旋会浪费大量的处理器资源

1. 1. 与线程阻塞相比，自旋会浪费大量的处理器资源。这是因为当前线程仍处于运行状况，只不过跑的是无用指令。它期望在运行无用指令的过程中，锁能够被释放出来。
    2. 我们可以用等红绿灯作为例子。Java 线程的阻塞相当于熄火停车，而自选状态相当于怠速停车。如果红灯的等待时间非常长，那么熄火停车相对省油一些；如果红灯的等待时间非常短，比如我们在同步代码块中只做了一个整型加法，那么在短时间内锁肯定会被释放出来，因此怠速停车更合适。
    3. 然而，对于JVM来说，它并不能看到红灯的剩余时间，也就没法根据等待时间的长短来选择是自旋还是阻塞。JVM给出的方案是自适应自旋，根据以往自旋等待时能否获取锁，来动态调整自旋的时间(循环数)。
    4. 就我们的例子来说，如果之前不熄火等待了绿灯，那么这次不熄火的时间就长一点；如果之前不熄火没等待绿灯，那么这次不熄火的时间就短一点。

1. 公平性

自旋状态还带来另外一个副作用，不公平的锁机制。处于阻塞状态的线程，无法立刻竞争被释放的锁。然而，处于

自旋状态的线程，则很有可能优先获得这把锁。



内建锁无法实现公平机制，而lock体系可以实现公平锁。



####  

### 2.5 死锁

同步的本质在于：一个线程等待另外一个线程执行完毕执行完成后才可以继续执行。但是如果现在相关的几个线程彼此之间都在等待着，那么就会造成死锁。



范例：观察死锁



```
package com.xuwei.threadLock;

/**
 * 死锁演示
 */
public class Demo04 {
    private static Pen pen = new Pen();
    private static  Book book = new Book();

    public static void main(String[] args) {

    }

    public void deadLock() {
        Thread t1 = new Thread(new Runnable() {
            @Override
            public void run() {
                synchronized (pen) {
                    System.out.println(Thread.currentThread()+" :我有笔，我就不给你");
                    synchronized (book) {
                        System.out.println(Thread.currentThread()+" :把你的本给我！");
                    }
                }
            }
        },"Pen");

        Thread t2 = new Thread(new Runnable() { // 本子线程
            @Override
            public void run() {
                synchronized (book) {
                    System.out.println(Thread.currentThread()+" :我有本子，我就不给你！");
                    synchronized (pen) {
                        System.out.println(Thread.currentThread()+" :把你的笔给我！");
                    }
                }
            }
        },"Book") ;
        t1.start();
        t2.start();

    }
}

class Pen {
    private String pen = "笔";
    public String getPen() {
        return pen;
    }
}

class Book {
    private String book = "本";
    public String getBook() {
        return book;
    }
}
```



死锁一旦出现之后，整个程序就将中断执行，所以死锁属于严重性问题。过多的同步会造成死锁，对于资源的上锁一定要注意不要成"环"



拓展：**银行家算法**